LICENSE.txt
setup.py
araby_gpt/ArabyGPT.py
araby_gpt/__init__.py
araby_gpt.egg-info/PKG-INFO
araby_gpt.egg-info/SOURCES.txt
araby_gpt.egg-info/dependency_links.txt
araby_gpt.egg-info/top_level.txt