Metadata-Version: 2.1
Name: araby-gpt
Version: 0.0.1
Summary: With this library, you can occur with artificial intelligence araby-gpt site in Python with ease
Author: sofi
Classifier: Programming Language :: Python :: 3
Classifier: Operating System :: OS Independent
Classifier: License :: OSI Approved :: MIT License
License-File: LICENSE.txt
